SecureHTTP.py
PySecureHTTP-1.0.1.data/scripts/generate_rsa_keys.sh
PySecureHTTP-1.0.1.dist-info/LICENSE
PySecureHTTP-1.0.1.dist-info/METADATA
PySecureHTTP-1.0.1.dist-info/WHEEL
PySecureHTTP-1.0.1.dist-info/entry_points.txt
PySecureHTTP-1.0.1.dist-info/top_level.txt
PySecureHTTP-1.0.1.dist-info/RECORD
